gpquant/Backtester.py
gpquant/Fitness.py
gpquant/Function.py
gpquant/SymbolicRegressor.py
gpquant/SyntaxTree.py
gpquant/__init__.py
gpquant-0.1.5.dist-info/METADATA
gpquant-0.1.5.dist-info/WHEEL
gpquant-0.1.5.dist-info/top_level.txt
gpquant-0.1.5.dist-info/RECORD
