Metadata-Version: 2.1
Name: gpquant
Version: 0.1.5
Summary: Genetic Programming for Quant
Home-page: https://github.com/UePG-21/gpquant
Author: UePG
Author-email: hanlin.warng@gmail.com
License: MIT
Classifier: Programming Language :: Python :: 3
Classifier: License :: OSI Approved :: MIT License
Classifier: Operating System :: OS Independent
